Workbook
Name temp: '[1]univ apc spend 2012-13'!#REF!

Sheet Cleaned
A1: PMID | B1: PMCID | C1: ID type | D1: Publisher | E1: Journal title | F1: Code | G1: Article title | H1: COST | I1: Links | J1: Gender | K1: County | L1: % Int | M1: % Ext | N1: Replies | O1: Check
B2: PMC3378987 | C2: PMC | D2: Elsevier | E2: Academy of Nutrition and Dietetics | F2: AND | G2: Parent support and parent mediated behaviours are associated with children's sugary beverage consumption | H2: 2379.54 | I2: 934 | J2: 0 | K2: 41 | L2: 0.94164318 | M2: 0.058356816 | N2: 0
B3: PMC3780468 | C3: PMC | D3: American Chemical Society | E3: ACS Chemical Biology | F3: CB | G3: A Novel Allosteric Inhibitor of the Uridine Diphosphate N-Acetylglucosamine Pyrophosphorylase from Trypanosoma brucei. | H3: 1294.59 | I3: 823 | J3: 0 | K3: 45 | L3: 0.67563786 | M3: 0.32436214 | N3: 0
B4: PMC3621575 | C4: PMC | D4: American Chemical Society | E4: ACS Chemical Biology | F4: CB | G4: Chemical proteomic analysis reveals the drugability of the kinome of Trypanosoma brucei. | H4: 1294.78 | I4: 866 | K4: 48 | L4: 0.98747019 | M4: 0.012529811 | N4: 0
C5: Blank | D5: American Chemical Society | E5: ACS Chemical Biology | F5: CB | G5: Discovery of β2 Adrenergic Receptor Ligands Using Biosensor Fragment Screening of Tagged Wild-Type Receptor | H5: 947.07 | I5: 76 | J5: 1 | K5: 11 | L5: 0.0036687967 | M5: 0.9963312 | N5: 0
A6: 24015914 | B6: PMC3833349 | C6: PMID + PMC | D6: American Chemical Society | E6: ACS Chemical Biology | F6: CB | G6: Discovery of an allosteric inhibitor binding site in 3-oxo-acyl-ACP reductase from Pseudomonas aeruginosa | H6: 1267.76 | J6: 1 | K6: 21 | L6: 0.08205373 | M6: 0.91794627 | N6: 0
B7: PMC3805332 | C7: PMC | D7: American Chemical Society | E7: ACS Chemical Biology | F7: CB | G7: Synthesis of alpha-glucan in mycobacteria involves a hetero-octameric complex of trehalose synthase TreS and maltokinase Pep2 | H7: 2286.73 | I7: 179 | J7: 0 | K7: 9 | L7: 0.64735029 | M7: 0.35264971 | N7: 0
B8: PMC3656742 | C8: PMC | D8: American Chemical Society | E8: ACS Chemical Neuroscience | F8: CN | G8: Continuous online microdialysis using microfluidic sensors: dynamic neuro-metabolic changes during spreading depolarisation | H8: 1186.8 | I8: 45 | J8: 1 | K8: 18 | L8: 0.42829475 | M8: 0.57170525 | N8: 0
B9: PMC3584654 | C9: PMC | D9: American Chemical Society | E9: ACS Nano | F9: NANO | G9: Hydroxy-terminated conjugated polymer nanoparticles have near-unity bright fraction | H9: 642.89 | I9: 60 | J9: 0 | K9: 17 | L9: 0.27927524 | M9: 0.72072476 | N9: 0
A10: 23373658 | C10: PMID | D10: American Chemical Society | E10: ACS Nano | F10: NANO | G10: Skin dendritic cell targeting via microneedle arrays laden with antigen-encapsulated poly-D,L-lactide-co-glycolide nanoparticles induces efficient antitumor and antiviral immune responses. | H10: 693.39 | I10: 606 | J10: 0 | L10: 0.84485895 | M10: 0.15514105 | N10: 0
B11: PMC3727331 | C11: PMC | D11: International Union of Crystallography | E11: Acta Crystallographica Section D: Biological Crystallography | F11: BIOC | G11: Clustering procedures for the optimal selection of data sets from multiple crystals in macromolecular crystallography | H11: 771.42 | I11: 480 | J11: 1 | K11: 22 | L11: 0.90950792 | M11: 0.090492082 | N11: 0
B12: PMC3565438 | C12: PMC | D12: International Union of Crystallography | E12: Acta Crystallographica Section D: Biological Crystallography | F12: BIOC | G12: Intensity statistics in the presence of translational non-crystallographic symmetry | H12: 773.74 | I12: 690 | J12: 1 | K12: 3 | L12: 0.65722673 | M12: 0.34277327 | N12: 0
B13: PMC3668577 | C13: PMC | D13: International Union of Crystallography | E13: Acta Crystallographica Section F: Structural Biology and Crystallization Communications | F13: STRUC | G13: Structure of diaminohydroxyphosphoribosylaminopyrimidine deaminase/5-amino-6-(5-phosphoribosylamino)uracil reductase from Acinetobacter baumannii. | H13: 785.6 | I13: 603 | K13: 32 | L13: 0.54983986 | M13: 0.45016014 | N13: 0
B14: PMC3606566 | C14: PMC | D14: International Union of Crystallography | E14: Acta Crystallographica Section F: Structural Biology and Crystallization Communications | F14: STRUC | G14: Structure of Pseudomonas aeruginosa inosine 5'-monophosphate dehydrogenase | H14: 807.67 | I14: 485 | J14: 0 | K14: 40 | L14: 0.5395541 | M14: 0.4604459 | N14: 0
B15: PMC3498934 | C15: PMC | D15: International Union of Crystallography | E15: Acta Crystallographica Section D: Biological Crystallography | F15: BIOC | G15: Nearest-cell: a fast and easy tool for locating crystal matches in the PDB. | H15: 757.18 | I15: 15 | J15: 0 | K15: 49 | L15: 0.9176209 | M15: 0.082379105 | N15: 0
A16: 22993091 | B16: PMC3447403 | C16: PMID + PMC | D16: International Union of Crystallography | E16: Acta Crystallographica Section D: Biological Crystallography | F16: BIOC | G16: Crystallization, dehydration and experimental phasing of WbdD, a bifunctional kinase and methyltransferase from Escherichia coli O9a | H16: 774.19 | I16: 376 | J16: 1 | K16: 15 | L16: 0.54700917 | M16: 0.45299083 | N16: 0
B17: PMC3087623 | C17: PMC | D17: International Union of Crystallography | E17: Acta Crystallographica Section D: Biological Crystallography | F17: ACTD | G17: Structure of HLA-A*0301 in complex with a peptide of proteolipid protein: insights into the role of HLA-A alleles in susceptibility to multiple sclerosis. | H17: 750.16 | I17: 904 | J17: 1 | K17: 19 | L17: 0.10131625 | M17: 0.89868375 | N17: 0
B18: PMC3808818 | C18: PMC | D18: Society for Publication of Acta Dermato-Venereologica | E18: Acta Dermato-Venereologica | F18: ACTV | G18: The Importance of a Full Clinical Examination: Assessment of Index Lesions Referred to a Skin Cancer Clinic Without a Total Body Skin Examination Would Miss One in Three Melanomas | H18: 653.96 | I18: 322 | J18: 1 | K18: 25 | L18: 0.18407886 | M18: 0.81592114 | N18: 0
A19: 23828613 | C19: PMID | D19: Springer | E19: Acta Diabetologica | F19: ACTD | G19: A rare SNP in pre-miR-34a is associated with increased levels of miR-34a in pancreatic beta cells | H19: 2336.28 | I19: 544 | J19: 0 | L19: 0.21081329 | M19: 0.78918671 | N19: 0
B20: PMC3374517 | C20: PMC | D20: International Union of Crystallography | E20: Acta Crystallographica Section F: Structural Biology and Crystallization Communications | F20: ACTF | G20: Crystallization and preliminary crystallographic analysis of the major capsid proteins VP16 and VP17 of bacteriophage P23-77 | H20: 754.9 | I20: 476 | J20: 1 | K20: 19 | L20: 0.29987596 | M20: 0.70012404 | N20: 0
B21: PMC3549237 | C21: PMC | D21: Springer | E21: Acta Neuropathologica | F21: ACTN | G21: Overexpression of human wild-type FUS causes progressive motor neuron degeneration in an age- and dose-dependent fashion | H21: 1901.04 | I21: 666 | J21: 0 | L21: 0.29481324 | M21: 0.70518676 | N21: 0
C22: Blank | D22: Springer | E22: Acta Neuropathologica | F22: ACTN | G22: α-Synucleinopathy associated with G51D SNCA mutation: A link between Parkinson's disease and multiple system atrophy? | H22: 1884.01 | I22: 94 | J22: 1 | K22: 10 | L22: 0.38723498 | M22: 0.61276502 | N22: 0
B23: PMC3661931 | C23: PMC | D23: Springer | E23: Acta Neuropathologica | F23: ACTN | G23: Insufficient OPC migration into demyelinated lesions is a cause of poor remyelination in MS and mouse models | H23: 2250.97 | I23: 62 | J23: 1 | K23: 26 | L23: 0.32758913 | M23: 0.67241087 | N23: 0
B24: PMC3535376 | C24: PMC | D24: Springer | E24: Acta Neuropathologica | F24: ACTN | G24: Unravelling the enigma o selective vulnerability in neurodegeneration: motor neurons resistant to degeneration in ALS show distinct gene expression characteristics and decreased susceptibility to excitotoxicity | I24: 188 | J24: 1 | K24: 34 | L24: 0.0191216 | M24: 0.9808784 | N24: 0
B25: PMC3798121 | C25: PMC | D25: Wiley | E25: Acta Ophthalmologica | F25: ACTO | G25: Visual and psychological morbidity among patients with autosomal dominant optic atrophy | H25: 2270.16 | I25: 764 | J25: 0 | K25: 15 | L25: 0.8045102 | M25: 0.1954898 | N25: 0
A26: 21624095 | B26: PMC3734623 | C26: PMID + PMC | D26: Wiley | E26: Acta Physiol | F26: ACTP | G26: Integration of transient receptor potential canonical channels with lipids | H26: 1991.5 | I26: 513 | J26: 0 | K26: 8 | L26: 0.34607205 | M26: 0.65392795 | N26: 0
C27: Blank | D27: Wiley | E27: Addiction | F27: ADCT | G27: Acute alcohol-related dysfunction as a predictor of employment status in a longitudinal study of working age men in Izhevsk, Russia. | H27: 1919.51 | I27: 180 | J27: 0 | K27: 43 | L27: 0.96653617 | M27: 0.033463833 | N27: 0
A28: 23734913 | C28: PMID | D28: Wiley | E28: Addiction | F28: ADCT | G28: Childhood conduct disorder trajectories, prior risk factors and cannabis use at age 16: birth cohort study | H28: 2352.94 | I28: 520 | J28: 0 | K28: 31 | L28: 0.086637113 | M28: 0.91336289 | N28: 0
C29: Blank | D29: Springer | E29: Advances in Experimental Medicine and Biology | F29: AEMB | G29: Wavelet cross-correlation to investigate regional variations in cerebral oxygenation in infants supported on extracorporeal membrane oxygenation | H29: 1928.45 | I29: 818 | J29: 0 | K29: 15 | L29: 0.78811469 | M29: 0.21188531 | N29: 0
C30: Blank | D30: Springer | E30: Advances in Experimental Medicine and Biology | F30: AEMB | G30: Modelling Cerebrovascular Reactivity: A Novel Near-Infrared Biomarker of Cerebral Autoregulation? | H30: 1928.46 | I30: 153 | J30: 1 | K30: 1 | L30: 0.46789626 | M30: 0.53210374 | N30: 0
C31: Blank | D31: Springer | E31: Advances in Experimental Medicine and Biology | F31: AEMB | G31: Normobaric hyperoxia does not change optical scattering or pathlength but does increase oxidised cytochrome C oxidase concentration in patients with brain injury | H31: 1928.46 | I31: 606 | J31: 0 | K31: 20 | L31: 0.32231037 | M31: 0.67768963 | N31: 0
C32: Blank | D32: Springer | E32: Advances in Experimental Medicine and Biology | F32: AEMB | G32: Oscillations in cerebral haemodynamics in patients with falciparum malaria | H32: 1928.46 | I32: 288 | J32: 1 | K32: 2 | L32: 0.45128438 | M32: 0.54871562 | N32: 0
A33: 21948184 | B33: PMC3528370 | C33: PMID + PMC | D33: Springer | E33: Age | F33: AGEA | G33: The dominant human conjunctival epithelial CD8αβ+ T cell population is maintained with age but the number of CD4+ T cells increases. | H33: 2338.28 | I33: 528 | J33: 1 | K33: 9 | L33: 0.26363814 | M33: 0.73636186 | N33: 0
A34: 23340916 | C34: PMID | D34: Springer | E34: Age | F34: AGEA | G34: Voluntary exercise can strengthen the circadian system in aged mice | H34: 2002 | I34: 420 | J34: 1 | K34: 45 | L34: 0.10124067 | M34: 0.89875933 | N34: 0
A35: 23672932 | B35: PMC3684112 | C35: PMID + PMC | D35: Oxford University Press | E35: Age and Ageing | F35: AGEA | G35: Early diagnosis and treatment of HIV infection: magnitude of benefit is greatest in older adults | H35: 2040 | I35: 371 | J35: 1 | K35: 25 | L35: 0.99817275 | M35: 0.0018272506 | N35: 0
C36: Blank | D36: Cambridge University Press | E36: Ageing and Society | F36: AGES | G36: Who cares? Implications of care-giving and -receiving by HIV-infected or -affected older | H36: 1695 | I36: 363 | J36: 0 | K36: 2 | L36: 0.88108645 | M36: 0.11891355 | N36: 0
C37: Blank | D37: Wiley | E37: Aging Cell | F37: AGIC | G37: TORC1 signaling inhibition by rapamycin and caffeine affect lifespan, global gene expression and cell proliferation of fission yeast | H37: 1970.57 | I37: 288 | K37: 41 | L37: 0.51888946 | M37: 0.48111054 | N37: 0
B38: PMC3713766 | C38: PMC | D38: Wolters Kluwer | E38: AIDS | F38: AIDAIDS | G38: HIV infected adolescents in Southern Africa can achieve good treatment outcomes: Results from a large retrospective cohort study. | H38: 1968.63 | I38: 372 | J38: 0 | K38: 27 | L38: 0.72814813 | M38: 0.27185187 | N38: 0
B39: PMC3748854 | C39: PMC | D39: Wolters Kluwer | E39: AIDS | F39: AIDAIDS | G39: Evaluation of an empiric risk screening score to identify acute and early HIV-1 infection among MSM in Coastal Kenya. | H39: 1834.77 | I39: 968 | J39: 0 | L39: 0.55407174 | M39: 0.44592826 | N39: 1582
B40: PMC3647051 | C40: PMC | D40: Wolters Kluwer | E40: AIDS | F40: AIDAIDS | G40: Grassroots Community Organisations' Contribution to the Scale-Up of HIV Testing and Counselling Services in Zimbabwe | H40: 2374.52 | I40: 202 | J40: 1 | K40: 20 | L40: 0.43837387 | M40: 0.56162613 | N40: 0
B41: PMC3633780 | C41: PMC | D41: Springer | E41: AIDS and Behavior | F41: AIDB | G41: Adherence to antiretroviral therapy and clinical outcomes among young adults reporting high-risk sexual behavior, including men who have sex with men, in coastal Kenya. | H41: 1834.77 | I41: 154 | J41: 1 | K41: 31 | L41: 0.76078286 | M41: 0.23921714 | N41: 998
C42: Blank | D42: Taylor and Francis | E42: Aids Care | F42: AIDC | G42: Burden of HIV among primary school children and feasibility of primary school-linked HIV testing in Harare, Zimbabwe. | H42: 2145.6 | I42: 223 | J42: 0 | K42: 33 | L42: 0.68969295 | M42: 0.31030705 | N42: 0
B43: PMC3590645 | C43: PMC | D43: Taylor and Francis | E43: Aids Care | F43: AIDC | G43: Asset ownership among households caring for orphans and vulnerable children in rural Zimbabwe: The influence of ownership on children's health and social vulnerabilities | H43: 2399.28 | I43: 124 | J43: 0 | K43: 10 | L43: 0.67490891 | M43: 0.32509109 | N43: 0
B44: PMC3613944 | C44: PMC | D44: Taylor and Francis | E44: Aids Care | F44: AIDC | G44: Barriers to involvement of men in ANC and VCT in Khayelitsha, South Africa. | H44: 2399.28 | I44: 47 | J44: 1 | K44: 41 | L44: 0.03207919 | M44: 0.96792081 | N44: 0
B45: PMC3687248 | C45: PMC | D45: Taylor and Francis | E45: Aids Care | F45: AIDC | G45: WORLDBANK Special Issue: Evidence for a contribution of the Community Response to HIV decline in eastern Zimbabwe? | H45: 2232.74 | I45: 906 | J45: 1 | K45: 42 | L45: 0.33505783 | M45: 0.66494217 | N45: 0
B46: PMC3819359 | C46: PMC | D46: Wolters Kluwer | E46: AIDS Journal | F46: AIDJ | G46: Short title: TB and VL breakthrough and failure. Orig title: Temporal association between incident tuberculosis and poor virological outcomes in a South African antiretroviral treatment service. | H46: 2015.72 | J46: 0 | K46: 13 | L46: 0.69217947 | M46: 0.30782053 | N46: 0
B47: PMC3765690 | C47: PMC | D47: BioMed Central | E47: AIDS Research and Therapy | F47: AIDSRT | G47: Collective Patient behaviours derailing ART rool-out in KwaZulu-Natal: Perspectives of Health Care Providers | H47: 1240 | I47: 187 | J47: 1 | K47: 19 | L47: 0.95668547 | M47: 0.043314531 | N47: 0
B48: PMC3815011 | C48: PMC | D48: Wolters Kluwer | E48: AIDS UK | F48: AIDUK | G48: HIV incidence and survival from age-specific seroprevalence after antiretroviral treatment scale up in rural South Africa | H48: 1836.92 | I48: 781 | J48: 1 | K48: 39 | L48: 0.49013333 | M48: 0.50986667 | N48: 0
B49: PMC3773237 | C49: PMC | D49: Wolters Kluwer | E49: AIDS UK | F49: AIDUK | G49: Sexual behaviour in a rural high HIV prevalence | H49: 1836.92 | I49: 220 | J49: 0 | K49: 36 | L49: 0.91862639 | M49: 0.081373607 | N49: 0
B50: PMC3633361 | C50: PMC | D50: Oxford University Press | E50: Alcohol and Alcoholism | F50: ALCA | G50: Post-treatment stage of change predicts 12-month outcome of treatment for alcohol problems | H50: 2040 | I50: 663 | J50: 0 | K50: 1 | L50: 0.26470402 | M50: 0.73529598 | N50: 0
B51: PMC3761189 | C51: PMC | D51: Wiley | E51: Alimentary Pharmacology and Therapeutics | F51: APT | G51: Predicting the development of acute kidney injury in liver cirrhosis--an analysis of glomerular filtration rate, proteinuria and kidney injury biomarkers. | H51: 2373.59 | J51: 1 | K51: 11 | L51: 0.87654668 | M51: 0.12345332 | N51: 0
B52: PMC3761188 | C52: PMC | D52: Wiley | E52: Alimentary Pharmacology and Therapeutics | F52: APT | G52: Meta-analysis: the diagnostic accuracy of critical flicker frequency in minimal hepatic encephalopathy | H52: 2373.59 | I52: 963 | J52: 0 | L52: 0.28264503 | M52: 0.71735497 | N52: 0
A53: 23514390 | C53: PMID | D53: Taylor and Francis | E53: American Journal of Bioethics | F53: AMB | G53: The "difficult patient" conundrum in sickle cell disease in Kenya: complex sociopolitical problems need wide multidimensional solutions. | H53: 1804.19 | I53: 896 | J53: 0 | K53: 4 | L53: 0.45372108 | M53: 0.54627892 | N53: 0
B54: PMC3516067 | C54: PMC | D54: The Sheridan Press | E54: American Journal of Tropical Medicine and Hygiene | F54: AJTMH | G54: Use of Rapid Diagnostic Tests in Malaria School Surveys in Kenya: Does their Under-performance Matter for Planning Malaria Control? | H54: 1152.5 | I54: 232 | J54: 1 | K54: 42 | L54: 0.91886064 | M54: 0.081139364 | N54: 0
A55: 23599091 | C55: PMID | D55: American Psychiatric Publishing | E55: American Journal of Psychiatry | F55: AJP | G55: High Loading of Polygenic Risk for ADHD in Children with Comorbid Aggression | H55: 2350.02 | I55: 898 | J55: 1 | L55: 0.076149394 | M55: 0.92385061 | N55: 0
A56: 22971149 | B56: PMC3466778 | C56: PMID + PMC | D56: American Chemical Society | E56: American Chemical Society | F56: AMES | G56: Characterizing the Fatty Acid Binding Site in the Cavity of Potassium Channel KcsA | H56: 1533.29 | I56: 836 | J56: 0 | K56: 6 | L56: 0.7816323 | M56: 0.2183677 | N56: 0
C57: Blank | D57: Wiley | E57: American Ethnologist | F57: AMEE | G57: This is our little Hajj? Muslim Holy sites and reappropriation of the sacred | H57: 1870.32 | I57: 577 | J57: 0 | K57: 40 | L57: 0.008244647 | M57: 0.99175535 | N57: 0
C58: Blank | D58: Wiley | E58: American Ethnologist | F58: AMEE | G58: Public secrets in public health: knowing not to know while making scientific . .. | H58: 1870.67 | I58: 902 | J58: 0 | K58: 9 | L58: 0.77091584 | M58: 0.22908416 | N58: 0
B59: PMC3639724 | C59: PMC | D59: Oxford University Press | E59: American Journal of Epidemiology | G59: Using a nonparametric multilevel latent Markov model to evaluate diagnostics for trachoma. | H59: 2040 | I59: 309 | J59: 0 | K59: 22 | L59: 0.40418154 | M59: 0.59581846 | N59: 0
B60: PMC3545681 | C60: PMC | D60: Dartmouth Journal Services | E60: American Journal of Clinical Nutrition | F60: AJCN | G60: Obesity is positively associated with dehydroepiandrosterone sulfate concentrations at 7 y in Chilean children of normal birth weight. | H60: 1891.19 | I60: 742 | J60: 0 | K60: 1 | L60: 0.77604858 | M60: 0.22395142 | N60: 0
B61: PMC3590646 | C61: PMC | D61: Taylor and Francis | E61: American Journal of Bioethics--Neuroscience | F61: AJBN | G61: Just How Cognitive is 'Cognitive Enhancement'? On the Significance of Emotions in University Students' Experiences with Study Drugs | H61: 2465.77 | I61: 598 | J61: 1 | L61: 0.24321979 | M61: 0.75678021 | N61: 0
B62: PMC3652920 | C62: PMC | D62: Dartmouth Journal Services | E62: American Journal of Clinical Nutrition | F62: AJCN | G62: DNA methylation potential: dietary intake and blood concentrations of one-carbon metabolites and cofactors in rural African women | H62: 1953.76 | I62: 353 | J62: 1 | K62: 39 | L62: 0.88438689 | M62: 0.11561311 | N62: 0
B63: PMC3813311 | C63: PMC | D63: Oxford University Press | E63: American Journal of Epidemiology | F63: AJE | G63: Prenatal exposures and anti-Müllerian hormone in female adolescents: the Avon Longitudinal Study of Parents and Children | H63: 2040 | I63: 963 | J63: 0 | K63: 40 | L63: 0.096936973 | M63: 0.90306303 | N63: 0
B64: PMC3132275 | C64: PMC | D64: Oxford University Press | E64: American Journal of Epidemiology | F64: AJE | G64: Association between urban life-years and cardiometabolic risk: the Indian migration study | H64: 2040 | I64: 626 | J64: 1 | L64: 0.54027735 | M64: 0.45972265 | N64: 0
B65: PMC3783091 | C65: PMC | D65: Oxford University Press | E65: American Journal of Epidemiology | F65: AJE | G65: Efficient design for Mendelian randomization studies: subsample and two-sample instrumental variable estimators | H65: 1700 | I65: 289 | J65: 1 | K65: 19 | L65: 0.78390843 | M65: 0.21609157 | N65: 0
A66: 23907068 | B66: PMC3837358 | C66: PMID + PMC | D66: Elsevier | E66: American Journal of Geriatric Psychiatry | F66: AJGP | G66: The epidemiology of delirium: challenges and opportunities for population studies | H66: 2404.53 | I66: 671 | J66: 1 | K66: 38 | L66: 0.21261847 | M66: 0.78738153 | N66: 0
B67: PMC3738821 | C67: PMC | D67: Cell Press | E67: American Journal of Human Genetics | F67: AJHG | G67: ELAC2 mutations cause a mitochondrial RNA processing defect associated with hypertrophic cardiomyopathy | H67: 2418.34 | I67: 865 | J67: 1 | K67: 31 | L67: 0.52011427 | M67: 0.47988573 | N67: 0
B68: PMC3516598 | C68: PMC | D68: Elsevier | E68: American Journal of Human Genetics | F68: AJHG | G68: Mutations in ANO3 cause dominant cranio-cervical dystonia: ion channel implicated in pathogenesis | H68: 2296.94 | I68: 522 | K68: 48 | L68: 0.66591685 | M68: 0.33408315 | N68: 0
B69: PMC3769921 | C69: PMC | D69: Elsevier | E69: American Journal of Human Genetics | F69: AJHG | G69: Mutations in FBXL4 cause mitochondrial encephalopathy and a disorder of mitochondrial DNA maintenance | H69: 2334.41 | I69: 658 | J69: 1 | K69: 12 | L69: 0.36606358 | M69: 0.63393642 | N69: 0
B70: PMC3591859 | C70: PMC | D70: Elsevier | E70: American Journal of Human Genetics | F70: AJHG | G70: Constitutional mutations in RTEL1 cause severe dyskeratosis congenita | H70: 2434.04 | I70: 14 | J70: 1 | K70: 17 | L70: 0.71742881 | M70: 0.28257119 | N70: 0
B71: PMC3567269 | C71: PMC | D71: Elsevier | E71: American Journal of Human Genetics | F71: AJHG | G71: LRIG2 Mutations Cause Urofacial Syndrome | H71: 3938.82 | I71: 714 | J71: 1 | K71: 19 | L71: 0.60827238 | M71: 0.39172762 | N71: 0
B72: PMC3470702 | C72: PMC | D72: Wiley | E72: American Journal of Medical Genetics | F72: AJMG | G72: A Novel Nonsense CDK5RAP2 Mutation in a Somali Child with Primary Microcephaly | H72: 2307.01 | I72: 756 | J72: 1 | K72: 41 | L72: 0.34304248 | M72: 0.65695752 | N72: 0
C73: Blank | D73: Wiley | E73: American Journal of Medical Genetics Part a | F73: AJMGPA | G73: A Distinct Mitochondrial Myopathy, Lactic Acidosis and Sideroblastic Anaemia (MLASA) Phenotype Associates with YARS2 Mutations | H73: 1500 | J73: 0 | L73: 0.59058505 | M73: 0.40941495 | N73: 0
B74: PMC3947303 | C74: PMC | D74: American Society for Investigative Pathology | E74: American Journal of Pathology | F74: AJP | G74: Trophoblast- and Vascular Smooth Muscle Cell-Derived MMP-12 Mediates Elastolysis during Uterine Spiral Artery Remodeling | H74: 995.31 | I74: 106 | J74: 1 | K74: 18 | L74: 0.17713949 | M74: 0.82286051 | N74: 0
A75: 22898127 | B75: PMC3830178 | C75: PMID + PMC | D75: Elsevier | E75: American Journal of Preventive Medicine | F75: AJPM | G75: Physical activity and transitioning to retirement: a systematic review | H75: 2377.65 | I75: 317 | J75: 0 | K75: 45 | L75: 0.43688484 | M75: 0.56311516 | N75: 0
A76: 23159264 | B76: PMC3834139 | C76: PMID + PMC | D76: Elsevier | E76: American Journal of Preventive Medicine | F76: AJPM | G76: Financial incentives to promote active travel: an evidence review and economic framework | H76: 2377.65 | I76: 210 | J76: 1 | K76: 32 | L76: 0.61042731 | M76: 0.38957269 | N76: 0
B77: PMC3708126 | C77: PMC | D77: Elsevier | E77: American Journal of Preventive Medicine | F77: AJPM | G77: Sickle Cell Disease in Africa; a neglected cause of early childhood mortality | H77: 1834.77 | I77: 825 | J77: 0 | L77: 0.34321372 | M77: 0.65678628 | N77: 0
C78: Blank | D78: American Psychiatric Association | E78: American Journal of Psychiatry | F78: AJP | G78: Methamphetamine-induced disruption of frontostriatal reward learning signals: relation to psychotic symptoms | H78: 2351.73 | K78: 19 | L78: 0.30198472 | M78: 0.69801528 | N78: 0
A79: 23409903 | C79: PMID | D79: American Public Health Association | E79: American Journal of Public Health | F79: AJPH | G79: Health co-benefits and transportation-related reductions in greenhouse gas emissions in the San Francisco bay area | H79: 1422.25 | I79: 217 | J79: 1 | K79: 22 | L79: 0.029030202 | M79: 0.9709698 | N79: 0
A80: 23331923 | C80: PMID | D80: Wiley | E80: American Journal of Transplantation | F80: AJT | G80: TNFa from classically activated macrophages accentuates epithelial to mesenchymal transitions in obliterative bronchiolitis | H80: 1884.3 | I80: 28 | J80: 0 | K80: 22 | L80: 0.64727692 | M80: 0.35272308 | N80: 0
B81: PMC3746108 | C81: PMC | D81: Wiley | E81: American Journal of Transplantation | F81: AJT | G81: Biliary epithelial senescence and plasticity in acute cellular rejection | H81: 2373.84 | I81: 419 | J81: 1 | K81: 20 | L81: 0.80848276 | M81: 0.19151724 | N81: 0
B82: PMC3440570 | C82: PMC | D82: Wiley | E82: American Journal of Transplantation | F82: AJT | G82: Low dose rapamycin treatment increases the ability of human regulatory T cells to inhibit transplant arteriosclerosis in vivo | H82: 1900.7 | I82: 68 | J82: 0 | K82: 8 | L82: 0.55484267 | M82: 0.44515733 | N82: 0
B83: PMC3752812 | C83: PMC | D83: The Sheridan Press | E83: American Journal of Tropical Medicine and Hygiene | F83: AJTMH | G83: Selection of antimalarial drug resistance after intermittent preventive treatment of infants and children (IPTi/c) in Senegal | H83: 1646.36 | I83: 109 | J83: 1 | L83: 0.58972685 | M83: 0.41027315 | N83: 0
B84: PMC3752809 | C84: PMC | D84: The Sheridan Press | E84: American Journal of Tropical Medicine and Hygiene | F84: AJTMH | G84: Asymptomatic Plasmodium infection and cognition among primary schoolchildren in a high malaria transmission setting in Uganda | H84: 1646.36 | I84: 517 | J84: 0 | K84: 42 | L84: 0.88776995 | M84: 0.11223005 | N84: 0
B85: PMC3516312 | C85: PMC | D85: The Sheridan Press | E85: American Journal of Tropical Medicine and Hygiene | F85: AJTMH | G85: Assessment of the Molecular Marker of Plasmodium falciparum Chloroquine Resistance in Senegal after several years of chloroquine withdrawal. | H85: 1651.3 | I85: 955 | J85: 0 | K85: 29 | L85: 0.44988666 | M85: 0.55011334 | N85: 0
C86: Blank | D86: American Society for Nutrition | E86: American Society for Nutrition | F86: ASN | G86: The association between breastfeeding and HIV on postpartum maternal weight changes over 24 months in rural South Africa | H86: 45.94 | I86: 896 | J86: 1 | K86: 41 | L86: 0.11062744 | M86: 0.88937256 | N86: 0
B87: PMC3475971 | C87: PMC | D87: Springer | E87: Analytical and Bioanalytical Chemistry | F87: ANAC | G87: Fragment screening of cyclin G-associated kinase by weak affinity chromatography. | H87: 1902.97 | I87: 988 | J87: 1 | K87: 2 | L87: 0.3537651 | M87: 0.6462349 | N87: 0
B88: PMC3740237 | C88: PMC | D88: Elsevier | E88: Analytical Biochemistry | F88: ANAB | G88: An expression system for screening of proteins for glycan and protein interactions. | H88: 2381.62 | I88: 171 | J88: 1 | L88: 0.76864345 | M88: 0.23135655 | N88: 0
B89: PMC3530960 | C89: PMC | D89: American Chemical Society | E89: Analytical Chemistry | G89: Variable-Pitch Rectangular Cross-section Radiofrequency Coils for the Nitrogen-14 Nuclear Quadrupole Resonance Investigation of Sealed Medicines Packets | H89: 759.67 | I89: 106 | J89: 1 | K89: 24 | L89: 0.26631866 | M89: 0.73368134 | N89: 0
A90: 23072351 | C90: PMID | D90: American Chemical Society | E90: Analytical Chemistry | G90: Amphipathic polymers facilitate the study of functional membrane in the gas phase | H90: 2082.74 | I90: 524 | J90: 0 | K90: 38 | L90: 0.96032763 | M90: 0.039672373 | N90: 0
B91: PMC3477822 | C91: PMC | D91: American Chemical Society | E91: Analytical Chemistry | G91: Quantitative dynamics of phosphorproteome: the devil is in the details | H91: 2314.1 | I91: 253 | J91: 0 | K91: 2 | L91: 0.15554746 | M91: 0.84445254 | N91: 0
A92: 23670821 | B92: PMC3738939 | C92: PMID + PMC | D92: Wiley | E92: Angewandte Chemie International Edition | F92: AIE | G92: Design and synthesis of cyclic ADP-4-thioribose as a stable equivalent of cyclic ADP-ribose, a calcium ion-mobilizing second messenger. | H92: 3026.17 | I92: 549 | J92: 0 | K92: 17 | L92: 0.120933 | M92: 0.879067 | N92: 0
B93: PMC3749465 | C93: PMC | D93: Wiley | E93: Angewandte Chemie International Edition | F93: ANGC | G93: Site-Specific Identification of the Abeta Fibril-Glycosaminoglycan Interaction Site using Solid State NMR Spectroscopy | H93: 2979.91 | I93: 66 | J93: 1 | K93: 2 | L93: 0.46722532 | M93: 0.53277468 | N93: 0
C94: Blank | D94: Wiley | E94: Angewandte Chemie International Edition | F94: ANGC | G94: Cysteine Promoted C-terminal Hydrazinolysis of Native Peptides and Proteins | H94: 2250 | I94: 985 | J94: 1 | K94: 28 | L94: 0.027110987 | M94: 0.97288901 | N94: 0
A95: 22961729 | B95: PMC3547296 | C95: PMID + PMC | D95: Wiley | E95: Angewandte Chemie International Edition | F95: ACIE | G95: Using ligand-mapping simulations to design a ligand selectively targeting a cryptic surface pocket of Polo-like kinase 1 | H95: 2437.19 | I95: 488 | J95: 1 | K95: 4 | L95: 0.65512135 | M95: 0.34487865 | N95: 0
A96: 22730171 | B96: PMC3556687 | C96: PMID + PMC | D96: Wiley | E96: Angewandte Chemie International Edition | F96: ACIE | G96: High-throughput interrogation of ligand binding mode using a fluorescence-based assay | H96: 2437.19 | I96: 432 | J96: 0 | K96: 36 | L96: 0.39412542 | M96: 0.60587458 | N96: 0
A97: 21472932 | B97: PMC3555362 | C97: PMID + PMC | D97: Wiley | E97: Angewandte Chemie International Edition | F97: ACIE | G97: From crystal-packing to molecular recognition: prediction and discovery of a binding site on the surface of Polo-like Kinase 1 | H97: 2437.19 | I97: 574 | J97: 1 | K97: 47 | L97: 0.20765139 | M97: 0.79234861 | N97: 0
B98: PMC3791410 | C98: PMC | D98: Elsevier | E98: Animal Behaviour | F98: ANIB | G98: Metabolic rate and body size are linked with perception of temporal information | H98: 1806.38 | I98: 778 | J98: 0 | K98: 15 | L98: 0.7891666 | M98: 0.2108334 | N98: 0
B99: PMC3763379 | C99: PMC | D99: Elsevier | E99: Animal Behaviour | F99: ANIB | G99: Faecal avoidance and selective foraging: Do wild mice have the luxury to avoid faeces? | H99: 1816.38 | I99: 418 | J99: 0 | L99: 0.10881948 | M99: 0.89118052 | N99: 0
B100: PMC3532623 | C100: PMC | D100: Wiley | E100: Annals of Human Genetics | F100: AHG | G100: Association of FTO gene variants with body composition in UK twins | H100: 2234.61 | I100: 774 | J100: 0 | K100: 11 | L100: 0.50211484 | M100: 0.49788516 | N100: 0
...

Sheet Summary
A1: Data2Clean - cleaning summary
A3: Identifier type (PMC / PMID / both / blank)
A4: ID type | B4: Rows | C4: Share
A5: PMC | B5: =COUNTIF(Cleaned!$C$2:$C$2128,A5) -> 1391 | C5: =B5/B$9 -> 0.65397273
A6: PMID | B6: =COUNTIF(Cleaned!$C$2:$C$2128,A6) -> 197 | C6: =B6/B$9 -> 0.092618712
A7: PMID + PMC | B7: =COUNTIF(Cleaned!$C$2:$C$2128,A7) -> 257 | C7: =B7/B$9 -> 0.12082746
A8: Blank | B8: =COUNTIF(Cleaned!$C$2:$C$2128,A8) -> 282 | C8: =B8/B$9 -> 0.1325811
A9: Total | B9: =SUM(B5:B8) -> 2127
A10: PMC present in total (PMC + both) | B10: =B5+B7 -> 1648
A11: PMID present in total (PMID + both) | B11: =B6+B7 -> 454
A13: Missing values: before vs after
A14: Column (original) | B14: Truly blank before | C14: 'na' text before | D14: Other placeholder text before | E14: Blank after | F14: 'na' text after
A15: PMID/PMCID | B15: 199 | C15: 0 | D15: 83 | E15: =COUNTBLANK(Cleaned!C2:C2128)*0+COUNTIF(Cleaned!C$2:C$2128,"Blank") -> 282 | F15: 0
A16: Publisher | B16: 0 | C16: 0 | D16: 0 | E16: =COUNTBLANK(Cleaned!D2:D2128) -> 0 | F16: =COUNTIF(Cleaned!D2:D2128,"na") -> 0
A17: Journal title | B17: 0 | C17: 1 | D17: 0 | E17: =COUNTBLANK(Cleaned!E2:E2128) -> 1 | F17: =COUNTIF(Cleaned!E2:E2128,"na") -> 0
A18: Code | B18: 67 | C18: 0 | D18: 0 | E18: =COUNTBLANK(Cleaned!F2:F2128) -> 67 | F18: =COUNTIF(Cleaned!F2:F2128,"na") -> 0
A19: Article title | B19: 0 | C19: 0 | D19: 0 | E19: =COUNTBLANK(Cleaned!G2:G2128) -> 0 | F19: =COUNTIF(Cleaned!G2:G2128,"na") -> 0
A20: COST | B20: 0 | C20: 0 | D20: 0 | E20: =COUNTBLANK(Cleaned!H2:H2128) -> 1 | F20: =COUNTIF(Cleaned!H2:H2128,"na") -> 0
A21: Links | B21: 206 | C21: 0 | D21: 0 | E21: =COUNTBLANK(Cleaned!I2:I2128) -> 206 | F21: =COUNTIF(Cleaned!I2:I2128,"na") -> 0
A22: Gender | B22: 66 | C22: 0 | D22: 0 | E22: =COUNTBLANK(Cleaned!J2:J2128) -> 66 | F22: =COUNTIF(Cleaned!J2:J2128,"na") -> 0
A23: County | B23: 0 | C23: 227 | D23: 0 | E23: =COUNTBLANK(Cleaned!K2:K2128) -> 227 | F23: =COUNTIF(Cleaned!K2:K2128,"na") -> 0
A24: % Int | B24: 0 | C24: 0 | D24: 0 | E24: =COUNTBLANK(Cleaned!L2:L2128) -> 0 | F24: =COUNTIF(Cleaned!L2:L2128,"na") -> 0
A25: % Ext | B25: 0 | C25: 0 | D25: 0 | E25: =COUNTBLANK(Cleaned!M2:M2128) -> 0 | F25: =COUNTIF(Cleaned!M2:M2128,"na") -> 0
A26: Replies | B26: 0 | C26: 0 | D26: 0 | E26: =COUNTBLANK(Cleaned!N2:N2128) -> 0 | F26: =COUNTIF(Cleaned!N2:N2128,"na") -> 0
A28: Rule applied: every missing value is an empty cell. 'na', '-', 'In Process', 'Pending', 'Epub ahead of print...' and similar placeholders were blanked.
A29: Price outlier fence (3 x IQR): above 5422. Row 24 (7,299,879.12) was removed as an obvious error; see Review.

Sheet Review
A1: Excel row | B1: Column | C1: Value | D1: Why it needs a human look
A2: 24 | B2: COST | C2: 7299879.12 | D2: ERROR: implausible cost removed (original 7,299,879.12)
A3: 86 | B3: COST | C3: 45.94 | D3: Review: very low cost (below 100)
A4: 1343 | B4: COST | C4: 13200 | D4: Review: very high cost (above 5422)
A5: 1931 | B5: COST | C5: 6000 | D5: Review: very high cost (above 5422)
A6: 2064 | B6: COST | C6: 5760 | D6: Review: very high cost (above 5422)
A7: 476 | B7: Publisher | C7: PubMed | D7: Not a recognisable publisher name (or unverified) - kept as is
A8: 587 | B8: Publisher | C8: Pion | D8: Not a recognisable publisher name (or unverified) - kept as is
A9: 882 | B9: Publisher | C9: Research Media Ltd | D9: Not a recognisable publisher name (or unverified) - kept as is
A10: 1189 | B10: Publisher | C10: Coaction | D10: Not a recognisable publisher name (or unverified) - kept as is
A11: 1192 | B11: Publisher | C11: Open Access Reg Ltd | D11: Not a recognisable publisher name (or unverified) - kept as is
A12: 1248 | B12: Publisher | C12: PubMed Central | D12: Not a recognisable publisher name (or unverified) - kept as is
A13: 1931 | B13: Publisher | C13: Public.service.co.uk | D13: Not a recognisable publisher name (or unverified) - kept as is
... A48: 1151 | B48: Article title | C48: Mast Cell subsets & their functional modulation by the Acanthocheilonema vitae product, ES... | D48: Citation text appended to the title - not removed

Sheet Publisher changes
A1: Original | B1: Cleaned | C1: Rows
A2: ACS | B2: American Chemical Society | C2: 7
A3: ACS (Amercian Chemical Society) Publications | B3: American Chemical Society | C3: 5
A4: ACS Publications | B4: American Chemical Society | C4: 2
A5: AMERICAN CHEMICAL SOCIETY | B5: American Chemical Society | C5: 1
A6: American Chemical Society Publications | B6: American Chemical Society | C6: 1
A7: The American Physiological Society | B7: American Physiological Society | C7: 1
A8: AMBSB | B8: American Society for Biochemistry and Molecular Biology | C8: 1
A9: American Soc for Biochemistry and Molecular Biology | B9: American Society for Biochemistry and Molecular Biology | C9: 1
A10: American Society for Biochemistry and Molecular Biolgy | B10: American Society for Biochemistry and Molecular Biology | C10: 1
A11: ASBMB | B11: American Society for Biochemistry and Molecular Biology | C11: 46
A12: ASBMB Cadmus | B12: American Society for Biochemistry and Molecular Biology | C12: 1
A13: ASBMB/Cadmus | B13: American Society for Biochemistry and Molecular Biology | C13: 1
... A194: Wolters Kluwers | B194: Wolters Kluwer | C194: 1

Sheet Journal changes
A1: Original | B1: Cleaned | C1: Rows
A2: ACS NANO | B2: ACS Nano | C2: 1
A3: Acta Crystallographica Section D, Biological Crystallography | B3: Acta Crystallographica Section D: Biological Crystallography | C3: 1
A4: Acta Crystallographica, Section D | B4: Acta Crystallographica Section D: Biological Crystallography | C4: 1
A5: Acta Crystallography D | B5: Acta Crystallographica Section D: Biological Crystallography | C5: 1
A6: Acta D | B6: Acta Crystallographica Section D: Biological Crystallography | C6: 1
A7: ACTA F | B7: Acta Crystallographica Section F: Structural Biology and Crystallization Communications | C7: 1
A8: Acta Dermato Venereologica | B8: Acta Dermato-Venereologica | C8: 1
A9: Acta Neuropathol | B9: Acta Neuropathologica | C9: 1
A10: Acta Opthalmologica | B10: Acta Ophthalmologica | C10: 1
A11: AGE | B11: Age | C11: 1
A12: Ageing & Society | B12: Ageing and Society | C12: 1
A13: AIDS Behav | B13: AIDS and Behavior | C13: 1
... A308: The Vet. Journal | B308: Veterinary Journal | C308: 1

Sheet ID changes
A1: Excel row | B1: Original PMID/PMCID | C1: PMID | D1: PMCID | E1: What was done
A2: 10 | B2: 23373658 | C2: 23373658 | E2: bare 8-digit number read as PMID
A3: 24 | B3: 3535376 | D3: PMC3535376 | E3: bare 7-digit number read as PMCID
A4: 26 | B4: 21624095 PMCID: PMC3734623 | C4: 21624095 | D4: PMC3734623 | E4: bare 8-digit number read as PMID
A5: 27 | B5: In Process | E5: not an ID, blanked: In Process
A6: 28 | B6: 23734913 | C6: 23734913 | E6: bare 8-digit number read as PMID
A7: 33 | B7: 21948184 PMC3528370 | C7: 21948184 | D7: PMC3528370 | E7: bare 8-digit number read as PMID
A8: 34 | B8: 23340916 | C8: 23340916 | E8: bare 8-digit number read as PMID
A9: 37 | B9: print published August 2013 | E9: not an ID, blanked: print published August 2013
A10: 39 | B10: 3748854 | D10: PMC3748854 | E10: bare 7-digit number read as PMCID
A11: 41 | B11: 3633780 | D11: PMC3633780 | E11: bare 7-digit number read as PMCID
A12: 42 | B12: In Process | E12: not an ID, blanked: In Process
A13: 53 | B13: 23514390 | C13: 23514390 | E13: bare 8-digit number read as PMID
A14: 54 | B14: 3516067 | D14: PMC3516067 | E14: bare 7-digit number read as PMCID
A15: 55 | B15: 23599091 | C15: 23599091 | E15: bare 8-digit number read as PMID
A16: 56 | B16: 22971149 PMC3466778 | C16: 22971149 | D16: PMC3466778 | E16: bare 8-digit number read as PMID
A17: 63 | B17: 3813311 | D17: PMC3813311 | E17: bare 7-digit number read as PMCID
A18: 71 | B18: 3567269 | D18: PMC3567269 | E18: bare 7-digit number read as PMCID
A19: 73 | B19: published Sept 2013 | E19: not an ID, blanked: published Sept 2013
A20: 74 | B20: 3947303 | D20: PMC3947303 | E20: bare 7-digit number read as PMCID
A21: 77 | B21: 3708126 | D21: PMC3708126 | E21: bare 7-digit number read as PMCID
A22: 79 | B22: PMID: 23409903 23409903 | C22: 23409903 | E22: bare 8-digit number read as PMID
A23: 90 | B23: 23072351 | C23: 23072351 | E23: bare 8-digit number read as PMID
A24: 92 | B24: 23670821 PMC3738939 | C24: 23670821 | D24: PMC3738939 | E24: bare 8-digit number read as PMID
A25: 114 | B25: 23877697 | C25: 23877697 | E25: bare 8-digit number read as PMID
A26: 117 | B26: 23758132 | C26: 23758132 | E26: bare 8-digit number read as PMID
A27: 118 | B27: Not yet available | E27: not an ID, blanked: Not yet available
A28: 119 | B28: 21903599 | C28: 21903599 | E28: bare 8-digit number read as PMID
A29: 120 | B29: 24061777 | C29: 24061777 | E29: bare 8-digit number read as PMID
A30: 125 | B30: 23740368 PMC3840700 | C30: 23740368 | D30: PMC3840700 | E30: bare 8-digit number read as PMID
A31: 126 | B31: 23460124 PMC3715109 | C31: 23460124 | D31: PMC3715109 | E31: bare 8-digit number read as PMID
A32: 129 | B32: In Process | E32: not an ID, blanked: In Process
A33: 134 | B33: 22302008 PMC3405838 | C33: 22302008 | D33: PMC3405838 | E33: bare 8-digit number read as PMID
A34: 139 | B34: 23025831 PMC3462035 | C34: 23025831 | D34: PMC3462035 | E34: bare 8-digit number read as PMID
A35: 140 | B35: 23731076 PMC3670620 | C35: 23731076 | D35: PMC3670620 | E35: bare 8-digit number read as PMID
A36: 141 | B36: 23244291 PMC3569044 | C36: 23244291 | D36: PMC3569044 | E36: bare 8-digit number read as PMID
A37: 145 | B37: 23162054 | C37: 23162054 | E37: bare 8-digit number read as PMID
A38: 146 | B38: 23713614 | C38: 23713614 | E38: bare 8-digit number read as PMID
A39: 150 | B39: 3685266 | D39: PMC3685266 | E39: bare 7-digit number read as PMCID
A40: 173 | B40: 23458425 PMC3630740 | C40: 23458425 | D40: PMC3630740 | E40: bare 8-digit number read as PMID
A41: 174 | B41: 3654172 | D41: PMC3654172 | E41: bare 7-digit number read as PMCID
A42: 178 | B42: 3847282 | D42: PMC3847282 | E42: bare 7-digit number read as PMCID
A43: 200 | B43: 3558749 | D43: PMC3558749 | E43: bare 7-digit number read as PMCID
A44: 203 | B44: 3744075 | D44: PMC3744075 | E44: bare 7-digit number read as PMCID
A45: 207 | B45: 22738332 PMC3381227 | C45: 22738332 | D45: PMC3381227 | E45: bare 8-digit number read as PMID
A46: 209 | B46: 23225165 | C46: 23225165 | E46: bare 8-digit number read as PMID
A47: 210 | B47: 23179061 | C47: 23179061 | E47: bare 8-digit number read as PMID
A48: 213 | B48: 23931322 PMCID: PMC3736666 | C48: 23931322 | D48: PMC3736666 | E48: bare 8-digit number read as PMID
A49: 214 | B49: 23877967 PMC3814418 | C49: 23877967 | D49: PMC3814418 | E49: bare 8-digit number read as PMID
A50: 229 | B50: 23002116 PMC3790949 | C50: 23002116 | D50: PMC3790949 | E50: bare 8-digit number read as PMID
A51: 231 | B51: 23255554 PMC3653566 | C51: 23255554 | D51: PMC3653566 | E51: bare 8-digit number read as PMID
A52: 232 | B52: 23043070 PMC3790942 | C52: 23043070 | D52: PMC3790942 | E52: bare 8-digit number read as PMID
A53: 239 | B53: 3526451 | D53: PMC3526451 | E53: bare 7-digit number read as PMCID
A54: 240 | B54: 3681581 | D54: PMC3681581 | E54: bare 7-digit number read as PMCID
A55: 241 | B55: 3708772 | D55: PMC3708772 | E55: bare 7-digit number read as PMCID
A56: 246 | B56: 3639180 | D56: PMC3639180 | E56: bare 7-digit number read as PMCID
A57: 248 | B57: 3570299 | D57: PMC3570299 | E57: bare 7-digit number read as PMCID
A58: 249 | B58: In Process | E58: not an ID, blanked: In Process
A59: 252 | B59: In Process | E59: not an ID, blanked: In Process
A60: 259 | B60: 3637822 | D60: PMC3637822 | E60: bare 7-digit number read as PMCID
A61: 260 | B61: 3751660 | D61: PMC3751660 | E61: bare 7-digit number read as PMCID
A62: 270 | B62: pub Aug 2013 | E62: not an ID, blanked: pub Aug 2013
A63: 293 | B63: 3752052 | D63: PMC3752052 | E63: bare 7-digit number read as PMCID
A64: 294 | B64: 3703578 | D64: PMC3703578 | E64: bare 7-digit number read as PMCID
A65: 297 | B65: 3526774 | D65: PMC3526774 | E65: bare 7-digit number read as PMCID
A66: 298 | B66: 3607215 | D66: PMC3607215 | E66: bare 7-digit number read as PMCID
A67: 306 | B67: in press | E67: not an ID, blanked: in press
A68: 323 | B68: 23246923 PMC3573228 | C68: 23246923 | D68: PMC3573228 | E68: bare 8-digit number read as PMID
A69: 326 | B69: Pub July 2013 | E69: not an ID, blanked: Pub July 2013
A70: 330 | B70: Not yet available | E70: not an ID, blanked: Not yet available
A71: 331 | B71: 3493860 | D71: PMC3493860 | E71: bare 7-digit number read as PMCID
A72: 334 | B72: 23701138 | C72: 23701138 | E72: bare 8-digit number read as PMID
A73: 335 | B73: published August 2013 | E73: not an ID, blanked: published August 2013
A74: 340 | B74: 23121507 PMCID: PMC3596649 | C74: 23121507 | D74: PMC3596649 | E74: bare 8-digit number read as PMID
A75: 342 | B75: 23763262 | C75: 23763262 | E75: bare 8-digit number read as PMID
A76: 345 | B76: 23703318 PMC3730114 | C76: 23703318 | D76: PMC3730114 | E76: bare 8-digit number read as PMID
A77: 349 | B77: 3489107 | D77: PMC3489107 | E77: bare 7-digit number read as PMCID
A78: 350 | B78: 23137768 | C78: 23137768 | E78: bare 8-digit number read as PMID
A79: 354 | B79: 3215872 | D79: PMC3215872 | E79: bare 7-digit number read as PMCID
A80: 357 | B80: 22962270 PMC3491872 | C80: 22962270 | D80: PMC3491872 | E80: bare 8-digit number read as PMID
A81: 358 | B81: 23892734 | C81: 23892734 | E81: bare 8-digit number read as PMID
A82: 367 | B82: 3505551 | D82: PMC3505551 | E82: bare 7-digit number read as PMCID
A83: 368 | B83: 19324410 | C83: 19324410 | E83: bare 8-digit number read as PMID
A84: 372 | B84: 23518502 PMC3674087 | C84: 23518502 | D84: PMC3674087 | E84: bare 8-digit number read as PMID
A85: 375 | B85: 3674354 | D85: PMC3674354 | E85: bare 7-digit number read as PMCID
A86: 376 | B86: 3730438 | D86: PMC3730438 | E86: bare 7-digit number read as PMCID
A87: 377 | B87: 3618382 | D87: PMC3618382 | E87: bare 7-digit number read as PMCID
A88: 381 | B88: 23328632 PMC3619236 | C88: 23328632 | D88: PMC3619236 | E88: bare 8-digit number read as PMID
A89: 382 | B89: 23498957 PMC3601332 | C89: 23498957 | D89: PMC3601332 | E89: bare 8-digit number read as PMID
A90: 396 | B90: PMID: 23041313 23041313 | C90: 23041313 | E90: bare 8-digit number read as PMID
A91: 405 | B91: Epub ahead of print pub Feb 2013, print in press | E91: not an ID, blanked: Epub ahead of print pub Feb 2013, print in press
A92: 406 | B92: 22533473 | C92: 22533473 | E92: bare 8-digit number read as PMID
A93: 408 | B93: 22897233 PMC3599488 | C93: 22897233 | D93: PMC3599488 | E93: bare 8-digit number read as PMID
A94: 409 | B94: 23126643 PMC3599488 | C94: 23126643 | D94: PMC3599488 | E94: bare 8-digit number read as PMID
A95: 410 | B95: 23902464 | C95: 23902464 | E95: bare 8-digit number read as PMID
A96: 416 | B96: Epub ahead of print - june 2013 | E96: not an ID, blanked: Epub ahead of print - june 2013
A97: 419 | B97: Epub ahead of print pub Nov 2012, print in press | E97: not an ID, blanked: Epub ahead of print pub Nov 2012, print in press
A98: 420 | B98: Epub ahead of print pub Jan 2013, print in press | E98: not an ID, blanked: Epub ahead of print pub Jan 2013, print in press
A99: 422 | B99: Epub ahead of print pub Jan 2013, print in press | E99: not an ID, blanked: Epub ahead of print pub Jan 2013, print in press
A100: 423 | B100: Epub ahead of print March 2013 - print in press | E100: not an ID, blanked: Epub ahead of print March 2013 - print in press
...

Sheet Original
A1: PMID/PMCID | B1: Publisher | C1: Journal title | D1: Code | E1: Article title | F1: COST | G1: Links | H1: Gender | I1: County | J1: % Int | K1: % Ext | L1: Replies
A2: PMC3378987 | B2: Elsevier | C2: Academy of Nutrition and Dietetics | D2: AND | E2: Parent support and parent mediated behaviours are associated with children's sugary beverage consumption | F2: 2379.54 | G2: 934 | H2: 0 | I2: 41 | J2: 0.94164318 | K2: 0.058356816 | L2: 0
A3: PMCID: PMC3780468 | B3: ACS (Amercian Chemical Society) Publications | C3: ACS Chemical Biology | D3: CB | E3: A Novel Allosteric Inhibitor of the Uridine Diphosphate N-Acetylglucosamine Pyrophosphorylase from Trypanosoma brucei. | F3: 1294.59 | G3: 823 | H3: 0 | I3: 45 | J3: 0.67563786 | K3: 0.32436214 | L3: 0
A4: PMCID: PMC3621575 | B4: ACS (Amercian Chemical Society) Publications | C4: ACS Chemical Biology | D4: CB | E4: Chemical proteomic analysis reveals the drugability of the kinome of Trypanosoma brucei. | F4: 1294.78 | G4: 866 | I4: 48 | J4: 0.98747019 | K4: 0.012529811 | L4: 0
B5: American Chemical Society | C5: ACS Chemical Biology | D5: CB | E5: Discovery of β2 Adrenergic Receptor Ligands Using Biosensor Fragment Screening of Tagged Wild-Type Receptor | F5: 947.07 | G5: 76 | H5: 1 | I5: 11 | J5: 0.0036687967 | K5: 0.9963312 | L5: 0
A6: PMID: 24015914 PMC3833349 | B6: American Chemical Society | C6: ACS Chemical Biology | D6: CB | E6: Discovery of an allosteric inhibitor binding site in 3-oxo-acyl-ACP reductase from Pseudomonas aeruginosa | F6: 1267.76 | H6: 1 | I6: 21 | J6: 0.08205373 | K6: 0.91794627 | L6: 0
A7: : PMC3805332 | B7: American Chemical Society | C7: ACS Chemical Biology | D7: CB | E7: Synthesis of alpha-glucan in mycobacteria involves a hetero-octameric complex of trehalose synthase TreS and maltokinase Pep2 | F7: 2286.73 | G7: 179 | H7: 0 | I7: 9 | J7: 0.64735029 | K7: 0.35264971 | L7: 0
A8: PMCID: PMC3656742 | B8: American Chemical Society | C8: ACS Chemical Neuroscience | D8: CN | E8: Continuous online microdialysis using microfluidic sensors: dynamic neuro-metabolic changes during spreading depolarisation | F8: 1186.8 | G8: 45 | H8: 1 | I8: 18 | J8: 0.42829475 | K8: 0.57170525 | L8: 0
A9: PMCID: 3584654 | B9: AMERICAN CHEMICAL SOCIETY | C9: ACS NANO | D9: NANO | E9: HYDROXY-TERMINATED CONJUGATED POLYMER NANOPARTICLES HAVE NEAR-UNITY BRIGHT FRACTION | F9: 642.89 | G9: 60 | H9: 0 | I9: 17 | J9: 0.27927524 | K9: 0.72072476 | L9: 0
A10: 23373658 | B10: American Chemical Society Publications | C10: ACS Nano | D10: NANO | E10: Skin dendritic cell targeting via microneedle arrays laden with antigen-encapsulated poly-D,L-lactide-co-glycolide nanoparticles induces efficient antitumor and antiviral immune responses. | F10: 693.39 | G10: 606 | H10: 0 | I10: na | J10: 0.84485895 | K10: 0.15514105 | L10: 0
A11: PMCID: PMC3727331 | B11: International Union of Crystallography | C11: Acta Crystallographica Section D, Biological Crystallography | D11: BIOC | E11: Clustering procedures for the optimal selection of data sets from multiple crystals in macromolecular crystallography | F11: 771.42 | G11: 480 | H11: 1 | I11: 22 | J11: 0.90950792 | K11: 0.090492082 | L11: 0
A12: PMCID: PMC3565438 | B12: International Union of Crystallography | C12: Acta Crystallographica Section D: Biological Crystallography | D12: BIOC | E12: Intensity statistics in the presence of translational non-crystallographic symmetry | F12: 773.74 | G12: 690 | H12: 1 | I12: 3 | J12: 0.65722673 | K12: 0.34277327 | L12: 0
A13: PMCID: PMC3668577 | B13: International Union of Crystallography (iucr) | C13: Acta Crystallographica Section F: Structural Biology and Crystallization Communications | D13: STRUC | E13: Structure of diaminohydroxyphosphoribosylaminopyrimidine deaminase/5-amino-6-(5-phosphoribosylamino)uracil reductase from Acinetobacter baumannii. | F13: 785.6 | G13: 603 | I13: 32 | J13: 0.54983986 | K13: 0.45016014 | L13: 0
A14: PMCID: PMC3606566 | B14: International Union of Crystallography (iucr) | C14: Acta Crystallographica Section F: Structural Biology and Crystallization Communications | D14: STRUC | E14: Structure of Pseudomonas aeruginosa inosine 5'-monophosphate dehydrogenase | F14: 807.67 | G14: 485 | H14: 0 | I14: 40 | J14: 0.5395541 | K14: 0.4604459 | L14: 0
A15: PMC3498934 | B15: International Union of Crystallography | C15: Acta Crystallographica, Section D | D15: BIOC | E15: Nearest-cell: a fast and easy tool for locating crystal matches in the PDB. | F15: 757.18 | G15: 15 | H15: 0 | I15: 49 | J15: 0.9176209 | K15: 0.082379105 | L15: 0
A16: PMID:22993091 PMC3447403 | B16: International Union of Crystallography | C16: Acta Crystallography D | D16: BIOC | E16: Crystallization, dehydration and experimental phasing of WbdD, a bifunctional kinase and methyltransferase from Escherichia coli O9a | F16: 774.19 | G16: 376 | H16: 1 | I16: 15 | J16: 0.54700917 | K16: 0.45299083 | L16: 0
A17: PMC3087623 | B17: International Union of Crystallography | C17: Acta D | D17: ACTD | E17: Structure of HLA-A*0301 in complex with a peptide of proteolipid protein: insights into the role of HLA-A alleles in susceptibility to multiple sclerosis. | F17: 750.16 | G17: 904 | H17: 1 | I17: 19 | J17: 0.10131625 | K17: 0.89868375 | L17: 0
A18: PMC3808818 | B18: Society for Publication of Acta Dermato-Venereologica | C18: Acta Dermato Venereologica | D18: ACTV | E18: The Importance of a Full Clinical Examination: Assessment of Index Lesions Referred to a Skin Cancer Clinic Without a Total Body Skin Examination Would Miss One in Three Melanomas | F18: 653.96 | G18: 322 | H18: 1 | I18: 25 | J18: 0.18407886 | K18: 0.81592114 | L18: 0
A19: PMID: 23828613 (July 2013 Epub) | B19: Springer | C19: Acta Diabetologica | D19: ACTD | E19: A rare SNP in pre-miR-34a is associated with increased levels of miR-34a in pancreatic beta cells | F19: $2336.28 | G19: 544 | H19: 0 | I19: na | J19: 0.21081329 | K19: 0.78918671 | L19: 0
A20: PMC3374517 | B20: International Union of Crystallography | C20: ACTA F | D20: ACTF | E20: Crystallization and preliminary crystallographic analysis of the major capsid proteins VP16 and VP17 of bacteriophage P23-77 | F20: 754.9 | G20: 476 | H20: 1 | I20: 19 | J20: 0.29987596 | K20: 0.70012404 | L20: 0
A21: PMC3549237 | B21: Springer | C21: Acta Neuropathol | D21: ACTN | E21: Overexpression of human wild-type FUS causes progressive motor neuron degeneration in an age- and dose-dependent fashion | F21: 1901.04 | G21: 666 | H21: 0 | I21: na | J21: 0.29481324 | K21: 0.70518676 | L21: 0
B22: Springer | C22: Acta Neuropathologica | D22: ACTN | E22: Î±-Synucleinopathy associated with G51D SNCA mutation: A link between Parkinson's disease and multiple system atrophy? | F22: 1884.01 | G22: 94 | H22: 1 | I22: 10 | J22: 0.38723498 | K22: 0.61276502 | L22: 0
A23: PMC3661931 | B23: Springer | C23: Acta Neuropathologica | D23: ACTN | E23: Insufficient OPC migration into demyelinated lesions is a cause of poor remyelination in MS and mouse models | F23: 2250.97 | G23: 62 | H23: 1 | I23: 26 | J23: 0.32758913 | K23: 0.67241087 | L23: 0
A24: 3535376 | B24: Springer | C24: Acta Neuropathologica | D24: ACTN | E24: Unravelling the enigma o selective vulnerability in neurodegeneration: motor neurons resistant to degeneration in ALS show distinct gene expression characteristics and decreased susceptibility to excitotoxicity | F24: 7299879.1 | G24: 188 | H24: 1 | I24: 34 | J24: 0.0191216 | K24: 0.9808784 | L24: 0
A25: PMC3798121 | B25: Wiley-Blackwell | C25: Acta Opthalmologica | D25: ACTO | E25: Visual and psychological morbidity among patients with autosomal dominant optic atrophy | F25: 2270.16 | G25: 764 | H25: 0 | I25: 15 | J25: 0.8045102 | K25: 0.1954898 | L25: 0
A26: 21624095 PMCID: PMC3734623 | B26: Wiley | C26: Acta Physiol | D26: ACTP | E26: Integration of transient receptor potential canonical channels with lipids | F26: 1991.5 | G26: 513 | H26: 0 | I26: 8 | J26: 0.34607205 | K26: 0.65392795 | L26: 0
A27: In Process | B27: Wiley | C27: Addiction | D27: ADCT | E27: Acute alcohol-related dysfunction as a predictor of employment status in a longitudinal study of working age men in Izhevsk, Russia. | F27: 1919.51 | G27: 180 | H27: 0 | I27: 43 | J27: 0.96653617 | K27: 0.033463833 | L27: 0
A28: 23734913 | B28: Wiley | C28: Addiction | D28: ADCT | E28: Childhood conduct disorder trajectories, prior risk factors and cannabis use at age 16: birth cohort study | F28: 2352.94 | G28: 520 | H28: 0 | I28: 31 | J28: 0.086637113 | K28: 0.91336289 | L28: 0
B29: Springer | C29: Advances in Experimental Medicine and Biology | D29: AEMB | E29: Wavelet cross-correlation to investigate regional variations in cerebral oxygenation in infants supported on extracorporeal membrane oxygenation | F29: 1928.45 | G29: 818 | H29: 0 | I29: 15 | J29: 0.78811469 | K29: 0.21188531 | L29: 0
B30: Springer | C30: Advances in Experimental Medicine and Biology | D30: AEMB | E30: Modelling Cerebrovascular Reactivity: A Novel Near-Infrared Biomarker of Cerebral Autoregulation? | F30: 1928.46 | G30: 153 | H30: 1 | I30: 1 | J30: 0.46789626 | K30: 0.53210374 | L30: 0
B31: Springer | C31: Advances in Experimental Medicine and Biology | D31: AEMB | E31: Normobaric hyperoxia does not change optical scattering or pathlength but does increase oxidised cytochrome C oxidase concentration in patients with brain injury | F31: 1928.46 | G31: 606 | H31: 0 | I31: 20 | J31: 0.32231037 | K31: 0.67768963 | L31: 0
B32: Springer | C32: Advances in Experimental Medicine and Biology | D32: AEMB | E32: Oscillations in cerebral haemodynamics in patients with falciparum malaria | F32: 1928.46 | G32: 288 | H32: 1 | I32: 2 | J32: 0.45128438 | K32: 0.54871562 | L32: 0
A33: 21948184 PMC3528370 | B33: SPRINGER-VERLAG GMBH | C33: Age | D33: AGEA | E33: The dominant human conjunctival epithelial CD8αβ+ T cell population is maintained with age but the number of CD4+ T cells increases. | F33: 2338.28 | G33: 528 | H33: 1 | I33: 9 | J33: 0.26363814 | K33: 0.73636186 | L33: 0
A34: 23340916 | B34: Springer-Verlag GMBH & Ci | C34: AGE | D34: AGEA | E34: Voluntary exercise can strengthen the circadian system in aged mice | F34: 2002 | G34: 420 | H34: 1 | I34: 45 | J34: 0.10124067 | K34: 0.89875933 | L34: 0
A35: PMID: 23672932 PMC3684112 | B35: Oxford University Press | C35: Age and Ageing | D35: AGEA | E35: Early diagnosis and treatment of HIV infection: magnitude of benefit is greatest in older adults | F35: 2040 | G35: 371 | H35: 1 | I35: 25 | J35: 0.99817275 | K35: 0.0018272506 | L35: 0
B36: Cambridge University Press | C36: Ageing & Society | D36: AGES | E36: Who cares? Implications of care-giving and -receiving by HIV-infected or -affected older | F36: 1695 | G36: 363 | H36: 0 | I36: 2 | J36: 0.88108645 | K36: 0.11891355 | L36: 0
A37: print published August 2013 | B37: Wiley | C37: Aging Cell | D37: AGIC | E37: TORC1 signaling inhibition by rapamycin and caffeine affect lifespan, global gene expression and cell proliferation of fission yeast | F37: 1970.57 | G37: 288 | I37: 41 | J37: 0.51888946 | K37: 0.48111054 | L37: 0
A38: PMC3713766 | B38: Wolters Kluwer | C38: AIDS | D38: AIDAIDS | E38: HIV infected adolescents in Southern Africa can achieve good treatment outcomes: Results from a large retrospective cohort study. | F38: 1968.63 | G38: 372 | H38: 0 | I38: 27 | J38: 0.72814813 | K38: 0.27185187 | L38: 0
A39: 3748854 | B39: Wolters Kluwer Health | C39: AIDS | D39: AIDAIDS | E39: Evaluation of an empiric risk screening score to identify acute and early HIV-1 infection among MSM in Coastal Kenya. | F39: $1834.77 | G39: 968 | H39: 0 | I39: na | J39: 0.55407174 | K39: 0.44592826 | L39: 1582
A40: PMCID: PMC3647051 | B40: Wolters Kluwer N.V./Lippinott | C40: AIDS | D40: AIDAIDS | E40: Grassroots Community Organisations' Contribution to the Scale-Up of HIV Testing and Counselling Services in Zimbabwe | F40: 2374.52 | G40: 202 | H40: 1 | I40: 20 | J40: 0.43837387 | K40: 0.56162613 | L40: 0
A41: 3633780 | B41: Springer | C41: AIDS Behav | D41: AIDB | E41: Adherence to antiretroviral therapy and clinical outcomes among young adults reporting high-risk sexual behavior, including men who have sex with men, in coastal Kenya. | F41: 1834.77 | G41: 154 | H41: 1 | I41: 31 | J41: 0.76078286 | K41: 0.23921714 | L41: 998
A42: In Process | B42: Taylor & Francis | C42: AIDS Care | D42: AIDC | E42: Burden of HIV among primary school children and feasibility of primary school-linked HIV testing in Harare, Zimbabwe. | F42: 2145.6 | G42: 223 | H42: 0 | I42: 33 | J42: 0.68969295 | K42: 0.31030705 | L42: 0
A43: PMCID: PMC3590645 | B43: Taylor & Francis | C43: Aids Care | D43: AIDC | E43: Asset ownership among households caring for orphans and vulnerable children in rural Zimbabwe: The influence of ownership on children's health and social vulnerabilities | F43: 2399.28 | G43: 124 | H43: 0 | I43: 10 | J43: 0.67490891 | K43: 0.32509109 | L43: 0
A44: PMCID: PMC3613944 | B44: Taylor & Francis | C44: Aids Care | D44: AIDC | E44: Barriers to involvement of men in ANC and VCT in Khayelitsha, South Africa. | F44: 2399.28 | G44: 47 | H44: 1 | I44: 41 | J44: 0.03207919 | K44: 0.96792081 | L44: 0
A45: PMCID: PMC3687248 | B45: Taylor and Francis | C45: AIDS Care | D45: AIDC | E45: WORLDBANK Special Issue: Evidence for a contribution of the Community Response to HIV decline in eastern Zimbabwe? | F45: 2232.74 | G45: 906 | H45: 1 | I45: 42 | J45: 0.33505783 | K45: 0.66494217 | L45: 0
A46: PMC3819359 | B46: Wolters Kluwer | C46: AIDS Journal | D46: AIDJ | E46: Short title: TB and VL breakthrough and failure. Orig title: Temporal association between incident tuberculosis and poor virological outcomes in a South African antiretroviral treatment service. | F46: 2015.72 | H46: 0 | I46: 13 | J46: 0.69217947 | K46: 0.30782053 | L46: 0
A47: PMC3765690 | B47: BioMed Central Limited | C47: AIDS Research and Therapy | D47: AIDSRT | E47: Collective Patient behaviours derailing ART rool-out in KwaZulu-Natal: Perspectives of Health Care Providers | F47: 1240 | G47: 187 | H47: 1 | I47: 19 | J47: 0.95668547 | K47: 0.043314531 | L47: 0
A48: PMC3815011 | B48: Wolters Kluwer | C48: AIDS UK | D48: AIDUK | E48: HIV incidence and survival from age-specific seroprevalence after antiretroviral treatment scale up in rural South Africa | F48: 1836.92 | G48: 781 | H48: 1 | I48: 39 | J48: 0.49013333 | K48: 0.50986667 | L48: 0
A49: PMC3773237 | B49: Wolters Kluwer | C49: AIDS UK | D49: AIDUK | E49: Sexual behaviour in a rural high HIV prevalence | F49: 1836.92 | G49: 220 | H49: 0 | I49: 36 | J49: 0.91862639 | K49: 0.081373607 | L49: 0
A50: PMC3633361 | B50: OUP | C50: Alcohol and Alcoholism | D50: ALCA | E50: Post-treatment stage of change predicts 12-month outcome of treatment for alcohol problems | F50: 2040 | G50: 663 | H50: 0 | I50: 1 | J50: 0.26470402 | K50: 0.73529598 | L50: 0
A51: PMCID: PMC3761189 | B51: Wiley | C51: Alimentrary Pharmacology & Therapeutics | D51: APT | E51: Predicting the development of acute kidney injury in liver cirrhosis--an analysis of glomerular filtration rate, proteinuria and kidney injury biomarkers. | F51: 2373.59 | H51: 1 | I51: 11 | J51: 0.87654668 | K51: 0.12345332 | L51: 0
A52: PMCID: PMC3761188 | B52: Wiley | C52: Alimentrary Pharmacology & Therapeutics | D52: APT | E52: Meta-analysis: the diagnostic accuracy of critical flicker frequency in minimal hepatic encephalopathy | F52: 2373.59 | G52: 963 | H52: 0 | I52: na | J52: 0.28264503 | K52: 0.71735497 | L52: 0
A53: 23514390 | B53: Taylor & Francis Journals | C53: Am J Bioeth | D53: AM B | E53: The "difficult patient" conundrum in sickle cell disease in Kenya: complex sociopolitical problems need wide multidimensional solutions. | F53: 1804.19 | G53: 896 | H53: 0 | I53: 4 | J53: 0.45372108 | K53: 0.54627892 | L53: 0
A54: 3516067 | B54: The Sheridan Press | C54: Am J Trop Med Hyg | D54: AJTMH | E54: Use of Rapid Diagnostic Tests in Malaria School Surveys in Kenya: Does their Under-performance Matter for Planning Malaria Control? | F54: 1152.5 | G54: 232 | H54: 1 | I54: 42 | J54: 0.91886064 | K54: 0.081139364 | L54: 0
A55: 23599091 | B55: American Psychiatric Publishing | C55: Americal Journal of Psychiatry | D55: AJP | E55: High Loading of Polygenic Risk for ADHD in Children with Comorbid Aggression | F55: 2350.02 | G55: 898 | H55: 1 | I55: na | J55: 0.076149394 | K55: 0.92385061 | L55: 0
A56: 22971149 PMC3466778 | B56: American Chemical Society | C56: American Chemical Society | D56: AMES | E56: Characterizing the Fatty Acid Binding Site in the Cavity of Potassium Channel KcsA | F56: 1533.29 | G56: 836 | H56: 0 | I56: 6 | J56: 0.7816323 | K56: 0.2183677 | L56: 0
B57: Wiley | C57: American Ethnologist | D57: AMEE | E57: This is our little Hajj? Muslim Holy sites and reappropriation of the sacred | F57: 1870.32 | G57: 577 | H57: 0 | I57: 40 | J57: 0.008244647 | K57: 0.99175535 | L57: 0
B58: Wiley | C58: American Ethnologist | D58: AMEE | E58: Public secrets in public health: knowing not to know while making scientific . .. | F58: 1870.67 | G58: 902 | H58: 0 | I58: 9 | J58: 0.77091584 | K58: 0.22908416 | L58: 0
A59: PMC3639724 | B59: OUP | C59: American Jnl Epidemiology | E59: Using a nonparametric multilevel latent Markov model to evaluate diagnostics for trachoma. | F59: 2040 | G59: 309 | H59: 0 | I59: 22 | J59: 0.40418154 | K59: 0.59581846 | L59: 0
A60: PMC3545681 | B60: Dartmouth Journal Services | C60: American Journal for Clinical Nutrition | D60: AJCN | E60: Obesity is positively associated with dehydroepiandrosterone sulfate concentrations at 7 y in Chilean children of normal birth weight. | F60: 1891.19 | G60: 742 | H60: 0 | I60: 1 | J60: 0.77604858 | K60: 0.22395142 | L60: 0
A61: PMC3590646 | B61: Taylor and Francis | C61: American Journal of Bioethics--Neuroscience | D61: AJBN | E61: Just How Cognitive is 'Cognitive Enhancement'? On the Significance of Emotions in University Students' Experiences with Study Drugs | F61: 2465.77 | G61: 598 | H61: 1 | I61: na | J61: 0.24321979 | K61: 0.75678021 | L61: 0
A62: PMC3652920 | B62: Dartmouth Journal Services | C62: American Journal of Clinical Nutrition | D62: AJCN | E62: DNA methylation potential: dietary intake and blood concentrations of one-carbon metabolites and cofactors in rural African women | F62: 1953.76 | G62: 353 | H62: 1 | I62: 39 | J62: 0.88438689 | K62: 0.11561311 | L62: 0
A63: 3813311 | B63: OUP | C63: American Journal of Epidemiology | D63: AJE | E63: Prenatal exposures and anti-Müllerian hormone in female adolescents: the Avon Longitudinal Study of Parents and Children | F63: 2040 | G63: 963 | H63: 0 | I63: 40 | J63: 0.096936973 | K63: 0.90306303 | L63: 0
A64: PMC3132275 | B64: OUP | C64: American Journal of Epidemiology | D64: AJE | E64: Association between urban life-years and cardiometabolic risk: the Indian migration study | F64: 2040 | G64: 626 | H64: 1 | I64: na | J64: 0.54027735 | K64: 0.45972265 | L64: 0
A65: PMCID: PMC3783091 | B65: Oxford University Press | C65: American Journal of Epidemiology | D65: AJE | E65: Efficient design for Mendelian randomization studies: subsample and two-sample instrumental variable estimators | F65: 1700 | G65: 289 | H65: 1 | I65: 19 | J65: 0.78390843 | K65: 0.21609157 | L65: 0
A66: PMID: 23907068 PMC3837358 | B66: Elsevier | C66: American Journal of Geriatric Psychiatry | D66: AJGP | E66: The epidemiology of delirium: challenges and opportunities for population studies | F66: 2404.53 | G66: 671 | H66: 1 | I66: 38 | J66: 0.21261847 | K66: 0.78738153 | L66: 0
A67: PMC3738821 | B67: Cell Press | C67: American Journal of Human Genetics | D67: AJHG | E67: ELAC2 mutations cause a mitochondrial RNA processing defect associated with hypertrophic cardiomyopathy | F67: 2418.34 | G67: 865 | H67: 1 | I67: 31 | J67: 0.52011427 | K67: 0.47988573 | L67: 0
A68: PMC3516598 | B68: Elsevier | C68: American Journal of Human Genetics | D68: AJHG | E68: Mutations in ANO3 cause dominant cranio-cervical dystonia: ion channel implicated in pathogenesis | F68: 2296.94 | G68: 522 | I68: 48 | J68: 0.66591685 | K68: 0.33408315 | L68: 0
A69: PMC3769921 | B69: Elsevier | C69: American Journal of Human Genetics | D69: AJHG | E69: Mutations in FBXL4 cause mitochondrial encephalopathy and a disorder of mitochondrial DNA maintenance | F69: 2334.41 | G69: 658 | H69: 1 | I69: 12 | J69: 0.36606358 | K69: 0.63393642 | L69: 0
A70: PMC3591859 | B70: Elsevier | C70: American Journal of Human Genetics | D70: AJHG | E70: Constitutional mutations in RTEL1 cause severe dyskeratosis congenita | F70: 2434.04 | G70: 14 | H70: 1 | I70: 17 | J70: 0.71742881 | K70: 0.28257119 | L70: 0
A71: 3567269 | B71: Elsevier | C71: American Journal of Human Genetics | D71: AJHG | E71: LRIG2 Mutations Cause Urofacial Syndrome | F71: 3938.82 | G71: 714 | H71: 1 | I71: 19 | J71: 0.60827238 | K71: 0.39172762 | L71: 0
A72: PMC3470702 | B72: John Wiley | C72: American Journal of Medical Genetics | D72: AJMG | E72: A Novel Nonsense CDK5RAP2 Mutation in a Somali Child with Primary Microcephaly | F72: 2307.01 | G72: 756 | H72: 1 | I72: 41 | J72: 0.34304248 | K72: 0.65695752 | L72: 0
A73: published Sept 2013 | B73: Wiley | C73: American Journal of Medical Genetics Part A | D73: AJMGPA | E73: A Distinct Mitochondrial Myopathy, Lactic Acidosis and Sideroblastic Anaemia (MLASA) Phenotype Associates with YARS2 Mutations | F73: 1500 | H73: 0 | I73: na | J73: 0.59058505 | K73: 0.40941495 | L73: 0
A74: 3947303 | B74: American Society for Investigative Pathology | C74: American Journal of Pathology | D74: AJP | E74: Trophoblast- and Vascular Smooth Muscle Cell-Derived MMP-12 Mediates Elastolysis during Uterine Spiral Artery Remodeling | F74: 995.31 | G74: 106 | H74: 1 | I74: 18 | J74: 0.17713949 | K74: 0.82286051 | L74: 0
A75: PMID: 22898127 PMC3830178 | B75: Elsevier | C75: American Journal of Preventive Medicine | D75: AJPM | E75: Physical activity and transitioning to retirement: a systematic review | F75: 2377.65 | G75: 317 | H75: 0 | I75: 45 | J75: 0.43688484 | K75: 0.56311516 | L75: 0
A76: PMID: 23159264 PMC3834139 | B76: Elsevier | C76: American Journal of Preventive Medicine | D76: AJPM | E76: Financial incentives to promote active travel: an evidence review and economic framework | F76: 2377.65 | G76: 210 | H76: 1 | I76: 32 | J76: 0.61042731 | K76: 0.38957269 | L76: 0
A77: 3708126 | B77: Elsevier | C77: American Journal of Preventive Medicine | D77: AJPM | E77: Sickle Cell Disease in Africa; a neglected cause of early childhood mortality | F77: 1834.77 | G77: 825 | H77: 0 | I77: na | J77: 0.34321372 | K77: 0.65678628 | L77: 0
B78: American Psychiatric Association | C78: American Journal of Psychiatry | D78: AJP | E78: Methamphetamine-induced disruption of frontostriatal reward learning signals: relation to psychotic symptoms | F78: 2351.73 | I78: 19 | J78: 0.30198472 | K78: 0.69801528 | L78: 0
A79: PMID: 23409903 23409903 | B79: American Public Health Association | C79: American Journal of Public Health | D79: AJPH | E79: Health co-benefits and transportation-related reductions in greenhouse gas emissions in the San Francisco bay area | F79: 1422.25 | G79: 217 | H79: 1 | I79: 22 | J79: 0.029030202 | K79: 0.9709698 | L79: 0
A80: PMID:23331923 | B80: Wiley-Blackwell | C80: American Journal of Transplantation | D80: AJT | E80: TNFa from classically activated macrophages accentuates epithelial to mesenchymal transitions in obliterative bronchiolitis | F80: 1884.3 | G80: 28 | H80: 0 | I80: 22 | J80: 0.64727692 | K80: 0.35272308 | L80: 0
A81: PMC3746108 | B81: Wiley-Blackwell | C81: American Journal of Transplantation | D81: AJT | E81: Biliary epithelial senescence and plasticity in acute cellular rejection | F81: 2373.84 | G81: 419 | H81: 1 | I81: 20 | J81: 0.80848276 | K81: 0.19151724 | L81: 0
A82: PMC3440570 | B82: Wiley-Blackwell, John Wiley & Sons | C82: American Journal of Transplantation | D82: AJT | E82: Low dose rapamycin treatment increases the ability of human regulatory T cells to inhibit transplant arteriosclerosis in vivo | F82: 1900.7 | G82: 68 | H82: 0 | I82: 8 | J82: 0.55484267 | K82: 0.44515733 | L82: 0
A83: PMC3752812 | B83: Sheridan Press | C83: American Journal of Tropical Medicine & Hygiene | D83: AJTMH | E83: Selection of antimalarial drug resistance after intermittent preventive treatment of infants and children (IPTi/c) in Senegal | F83: 1646.36 | G83: 109 | H83: 1 | I83: na | J83: 0.58972685 | K83: 0.41027315 | L83: 0
A84: PMC3752809 | B84: Sheridan Press | C84: American Journal of Tropical Medicine & Hygiene | D84: AJTMH | E84: Asymptomatic Plasmodium infection and cognition among primary schoolchildren in a high malaria transmission setting in Uganda | F84: 1646.36 | G84: 517 | H84: 0 | I84: 42 | J84: 0.88776995 | K84: 0.11223005 | L84: 0
A85: PMC3516312 | B85: Sheridan Press | C85: American Journal of Tropical Medicine & Hygiene | D85: AJTMH | E85: Assessment of the Molecular Marker of Plasmodium falciparum Chloroquine Resistance in Senegal after several years of chloroquine withdrawal. | F85: 1651.3 | G85: 955 | H85: 0 | I85: 29 | J85: 0.44988666 | K85: 0.55011334 | L85: 0
B86: American Society for Nutrition | C86: American Society for Nutrition | D86: ASN | E86: The association between breastfeeding and HIV on postpartum maternal weight changes over 24 months in rural South Africa | F86: 45.94 | G86: 896 | H86: 1 | I86: 41 | J86: 0.11062744 | K86: 0.88937256 | L86: 0
A87: PMC3475971 | B87: Springer | C87: Anal Bioanal Chem. | D87: ANAC | E87: Fragment screening of cyclin G-associated kinase by weak affinity chromatography. | F87: 1902.97 | G87: 988 | H87: 1 | I87: 2 | J87: 0.3537651 | K87: 0.6462349 | L87: 0
A88: PMCID: PMC3740237 | B88: Elsevier | C88: Analytical Biochemistry | D88: ANAB | E88: An expression system for screening of proteins for glycan and protein interactions. | F88: 2381.62 | G88: 171 | H88: 1 | I88: na | J88: 0.76864345 | K88: 0.23135655 | L88: 0
A89: PMC3530960 | B89: American Chemical Society | C89: Analytical Chemistry | E89: Variable-Pitch Rectangular Cross-section Radiofrequency Coils for the Nitrogen-14 Nuclear Quadrupole Resonance Investigation of Sealed Medicines Packets | F89: 759.67 | G89: 106 | H89: 1 | I89: 24 | J89: 0.26631866 | K89: 0.73368134 | L89: 0
A90: 23072351 | B90: American Chemical Society | C90: Analytical Chemistry | E90: Amphipathic polymers facilitate the study of functional membrane in the gas phase | F90: 2082.74 | G90: 524 | H90: 0 | I90: 38 | J90: 0.96032763 | K90: 0.039672373 | L90: 0
A91: PMC3477822 | B91: American Chemical Society | C91: Analytical Chemistry | E91: Quantitative dynamics of phosphorproteome: the devil is in the details | F91: 2314.1 | G91: 253 | H91: 0 | I91: 2 | J91: 0.15554746 | K91: 0.84445254 | L91: 0
A92: 23670821 PMC3738939 | B92: Wiley-VCH | C92: Angew chems Int Ed | D92: AIE | E92: Design and synthesis of cyclic ADP-4-thioribose as a stable equivalent of cyclic ADP-ribose, a calcium ion-mobilizing second messenger. | F92: 3026.17 | G92: 549 | H92: 0 | I92: 17 | J92: 0.120933 | K92: 0.879067 | L92: 0
A93: PMC3749465 | B93: Wiley | C93: Angewande Chemie | D93: ANGC | E93: Site-Specific Identification of the Abeta Fibril-Glycosaminoglycan Interaction Site using Solid State NMR Spectroscopy | F93: 2979.91 | G93: 66 | H93: 1 | I93: 2 | J93: 0.46722532 | K93: 0.53277468 | L93: 0
B94: Wiley | C94: Angewandte Chemie | D94: ANGC | E94: Cysteine Promoted C-terminal Hydrazinolysis of Native Peptides and Proteins | F94: 2250 | G94: 985 | H94: 1 | I94: 28 | J94: 0.027110987 | K94: 0.97288901 | L94: 0
A95: PMID:22961729 PMC3547296 | B95: Wiley-Blackwell | C95: Angewandte Chemie International Edition | D95: ACIE | E95: Using ligand-mapping simulations to design a ligand selectively targeting a cryptic surface pocket of Polo-like kinase 1 | F95: 2437.19 | G95: 488 | H95: 1 | I95: 4 | J95: 0.65512135 | K95: 0.34487865 | L95: 0
A96: PMID:22730171 PMC3556687 | B96: Wiley-Blackwell | C96: Angewandte Chemie International Edition | D96: ACIE | E96: High-throughput interrogation of ligand binding mode using a fluorescence-based assay | F96: 2437.19 | G96: 432 | H96: 0 | I96: 36 | J96: 0.39412542 | K96: 0.60587458 | L96: 0
A97: PMID:21472932 PMC3555362 | B97: Wiley-Blackwell | C97: Angewandte Chemie International Edition | D97: ACIE | E97: From crystal-packing to molecular recognition: prediction and discovery of a binding site on the surface of Polo-like Kinase 1 | F97: 2437.19 | G97: 574 | H97: 1 | I97: 47 | J97: 0.20765139 | K97: 0.79234861 | L97: 0
A98: PMC3791410 | B98: Elsevier | C98: Animal Behaviour | D98: ANIB | E98: Metabolic rate and body size are linked with perception of temporal information | F98: 1806.38 | G98: 778 | H98: 0 | I98: 15 | J98: 0.7891666 | K98: 0.2108334 | L98: 0
A99: PMC3763379 | B99: Elsevier | C99: Animal Behaviour | D99: ANIB | E99: Faecal avoidance and selective foraging: Do wild mice have the luxury to avoid faeces? | F99: 1816.38 | G99: 418 | H99: 0 | I99: na | J99: 0.10881948 | K99: 0.89118052 | L99: 0
A100: PMC3532623 | B100: Wiley | C100: Annals of Human Genetics | D100: AHG | E100: Association of FTO gene variants with body composition in UK twins | F100: 2234.61 | G100: 774 | H100: 0 | I100: 11 | J100: 0.50211484 | K100: 0.49788516 | L100: 0
...
